{
  "cnn": [
    {
      "epoch": 0,
      "train_loss": 0.029184867616654956,
      "val_rmse_mm": [
        1.534,
        1.796,
        1.485
      ]
    },
    {
      "epoch": 1,
      "train_loss": 0.020381520953866236,
      "val_rmse_mm": [
        1.499,
        1.398,
        1.237
      ]
    },
    {
      "epoch": 2,
      "train_loss": 0.018791982755370255,
      "val_rmse_mm": [
        1.456,
        1.436,
        1.575
      ]
    },
    {
      "epoch": 3,
      "train_loss": 0.017787738378634812,
      "val_rmse_mm": [
        1.507,
        1.362,
        1.258
      ]
    },
    {
      "epoch": 4,
      "train_loss": 0.01703306332471354,
      "val_rmse_mm": [
        1.461,
        1.37,
        1.223
      ]
    },
    {
      "epoch": 5,
      "train_loss": 0.016465027184653334,
      "val_rmse_mm": [
        1.329,
        1.247,
        1.184
      ]
    },
    {
      "epoch": 6,
      "train_loss": 0.015902493269435162,
      "val_rmse_mm": [
        1.447,
        1.441,
        1.172
      ]
    },
    {
      "epoch": 7,
      "train_loss": 0.01556245488149185,
      "val_rmse_mm": [
        1.279,
        1.375,
        1.213
      ]
    },
    {
      "epoch": 8,
      "train_loss": 0.015075732907868135,
      "val_rmse_mm": [
        1.328,
        1.263,
        1.156
      ]
    },
    {
      "epoch": 9,
      "train_loss": 0.014727189206817922,
      "val_rmse_mm": [
        1.252,
        1.233,
        1.131
      ]
    },
    {
      "epoch": 10,
      "train_loss": 0.014427713172904314,
      "val_rmse_mm": [
        1.275,
        1.241,
        1.162
      ]
    },
    {
      "epoch": 11,
      "train_loss": 0.014112960552748343,
      "val_rmse_mm": [
        1.287,
        1.229,
        1.138
      ]
    },
    {
      "epoch": 12,
      "train_loss": 0.013899372197346882,
      "val_rmse_mm": [
        1.245,
        1.223,
        1.125
      ]
    },
    {
      "epoch": 13,
      "train_loss": 0.013639368061706257,
      "val_rmse_mm": [
        1.246,
        1.216,
        1.139
      ]
    },
    {
      "epoch": 14,
      "train_loss": 0.013319112460928074,
      "val_rmse_mm": [
        1.243,
        1.227,
        1.118
      ]
    },
    {
      "epoch": 15,
      "train_loss": 0.013104113031986995,
      "val_rmse_mm": [
        1.245,
        1.214,
        1.12
      ]
    },
    {
      "epoch": 16,
      "train_loss": 0.012881416836488205,
      "val_rmse_mm": [
        1.258,
        1.243,
        1.11
      ]
    },
    {
      "epoch": 17,
      "train_loss": 0.012625841479510902,
      "val_rmse_mm": [
        1.233,
        1.217,
        1.115
      ]
    },
    {
      "epoch": 18,
      "train_loss": 0.0123878013222349,
      "val_rmse_mm": [
        1.22,
        1.231,
        1.116
      ]
    },
    {
      "epoch": 19,
      "train_loss": 0.012145553840413284,
      "val_rmse_mm": [
        1.218,
        1.206,
        1.114
      ]
    },
    {
      "epoch": 20,
      "train_loss": 0.011934499531505712,
      "val_rmse_mm": [
        1.214,
        1.201,
        1.126
      ]
    },
    {
      "epoch": 21,
      "train_loss": 0.011706990200313938,
      "val_rmse_mm": [
        1.23,
        1.211,
        1.116
      ]
    },
    {
      "epoch": 22,
      "train_loss": 0.011496800331959078,
      "val_rmse_mm": [
        1.23,
        1.217,
        1.121
      ]
    },
    {
      "epoch": 23,
      "train_loss": 0.011304630950749645,
      "val_rmse_mm": [
        1.214,
        1.201,
        1.117
      ]
    },
    {
      "epoch": 24,
      "train_loss": 0.011122235012297395,
      "val_rmse_mm": [
        1.216,
        1.205,
        1.125
      ]
    },
    {
      "epoch": 25,
      "train_loss": 0.010975898251365362,
      "val_rmse_mm": [
        1.218,
        1.202,
        1.119
      ]
    },
    {
      "epoch": 26,
      "train_loss": 0.01084114885689262,
      "val_rmse_mm": [
        1.218,
        1.201,
        1.119
      ]
    },
    {
      "epoch": 27,
      "train_loss": 0.010743883072612984,
      "val_rmse_mm": [
        1.213,
        1.201,
        1.119
      ]
    },
    {
      "epoch": 28,
      "train_loss": 0.010674840291243978,
      "val_rmse_mm": [
        1.214,
        1.202,
        1.12
      ]
    },
    {
      "epoch": 29,
      "train_loss": 0.010635004542949206,
      "val_rmse_mm": [
        1.214,
        1.201,
        1.12
      ]
    }
  ],
  "mlp": [
    {
      "epoch": 0,
      "train_loss": 0.13877530646126407,
      "val_rmse_mm": [
        2.68,
        2.601,
        3.677
      ]
    },
    {
      "epoch": 1,
      "train_loss": 0.06210487414779001,
      "val_rmse_mm": [
        2.295,
        2.293,
        3.446
      ]
    },
    {
      "epoch": 2,
      "train_loss": 0.051221382653600565,
      "val_rmse_mm": [
        2.044,
        2.064,
        2.596
      ]
    },
    {
      "epoch": 3,
      "train_loss": 0.04157602228187347,
      "val_rmse_mm": [
        1.912,
        1.929,
        2.247
      ]
    },
    {
      "epoch": 4,
      "train_loss": 0.03522882704239522,
      "val_rmse_mm": [
        1.83,
        1.766,
        2.021
      ]
    },
    {
      "epoch": 5,
      "train_loss": 0.031193628488782495,
      "val_rmse_mm": [
        1.764,
        1.728,
        1.813
      ]
    },
    {
      "epoch": 6,
      "train_loss": 0.028606016119800133,
      "val_rmse_mm": [
        1.7,
        1.682,
        1.715
      ]
    },
    {
      "epoch": 7,
      "train_loss": 0.026963357476297328,
      "val_rmse_mm": [
        1.734,
        1.672,
        1.631
      ]
    },
    {
      "epoch": 8,
      "train_loss": 0.025914557280249002,
      "val_rmse_mm": [
        1.701,
        1.657,
        1.598
      ]
    },
    {
      "epoch": 9,
      "train_loss": 0.02492798023136603,
      "val_rmse_mm": [
        1.639,
        1.607,
        1.643
      ]
    },
    {
      "epoch": 10,
      "train_loss": 0.024272480718094732,
      "val_rmse_mm": [
        1.635,
        1.574,
        1.54
      ]
    },
    {
      "epoch": 11,
      "train_loss": 0.02368430173445911,
      "val_rmse_mm": [
        1.645,
        1.566,
        1.563
      ]
    },
    {
      "epoch": 12,
      "train_loss": 0.022992804271525568,
      "val_rmse_mm": [
        1.58,
        1.566,
        1.512
      ]
    },
    {
      "epoch": 13,
      "train_loss": 0.02246441867582411,
      "val_rmse_mm": [
        1.581,
        1.547,
        1.525
      ]
    },
    {
      "epoch": 14,
      "train_loss": 0.022156765992607887,
      "val_rmse_mm": [
        1.566,
        1.537,
        1.442
      ]
    },
    {
      "epoch": 15,
      "train_loss": 0.021733487624160226,
      "val_rmse_mm": [
        1.548,
        1.56,
        1.416
      ]
    },
    {
      "epoch": 16,
      "train_loss": 0.02143739829299435,
      "val_rmse_mm": [
        1.539,
        1.502,
        1.419
      ]
    },
    {
      "epoch": 17,
      "train_loss": 0.0210983370128,
      "val_rmse_mm": [
        1.528,
        1.49,
        1.42
      ]
    },
    {
      "epoch": 18,
      "train_loss": 0.02084767954785572,
      "val_rmse_mm": [
        1.531,
        1.493,
        1.406
      ]
    },
    {
      "epoch": 19,
      "train_loss": 0.020608739203083273,
      "val_rmse_mm": [
        1.515,
        1.477,
        1.414
      ]
    },
    {
      "epoch": 20,
      "train_loss": 0.02042846845719092,
      "val_rmse_mm": [
        1.524,
        1.474,
        1.382
      ]
    },
    {
      "epoch": 21,
      "train_loss": 0.020268744847352377,
      "val_rmse_mm": [
        1.503,
        1.48,
        1.379
      ]
    },
    {
      "epoch": 22,
      "train_loss": 0.0200649291866833,
      "val_rmse_mm": [
        1.504,
        1.468,
        1.382
      ]
    },
    {
      "epoch": 23,
      "train_loss": 0.019934135279339685,
      "val_rmse_mm": [
        1.5,
        1.463,
        1.379
      ]
    },
    {
      "epoch": 24,
      "train_loss": 0.019804187413834627,
      "val_rmse_mm": [
        1.492,
        1.46,
        1.377
      ]
    },
    {
      "epoch": 25,
      "train_loss": 0.01972835967674833,
      "val_rmse_mm": [
        1.492,
        1.459,
        1.372
      ]
    },
    {
      "epoch": 26,
      "train_loss": 0.0196380549426904,
      "val_rmse_mm": [
        1.491,
        1.456,
        1.356
      ]
    },
    {
      "epoch": 27,
      "train_loss": 0.019582182541588083,
      "val_rmse_mm": [
        1.49,
        1.453,
        1.355
      ]
    },
    {
      "epoch": 28,
      "train_loss": 0.0195358971599274,
      "val_rmse_mm": [
        1.489,
        1.454,
        1.353
      ]
    },
    {
      "epoch": 29,
      "train_loss": 0.019510817791404653,
      "val_rmse_mm": [
        1.487,
        1.453,
        1.352
      ]
    }
  ]
}