{
  "model": "delta ~ f_core*N(0,sigma1) + (1-f_core)*N(0,sigma2), per coordinate, mm",
  "acceptance_is_per_single_photon_efficiency": true,
  "efficiency_ladder_per_shot_gamma": {
    "CsI(Tl)": {
      "interacts": 0.781,
      "full_energy_given_interacting": 0.653,
      "window_given_full_energy": 0.954
    },
    "BGO": {
      "interacts": 0.868,
      "full_energy_given_interacting": 0.87,
      "window_given_full_energy": 0.954
    }
  },
  "source": "CryspLight window samples; shapes frozen to the no-selection two-Gaussian fits",
  "scanners": {
    "CsI(Tl)": {
      "none": {
        "efficiency": 1.0,
        "coords": {
          "x": {
            "sigma1_mm": 1.119,
            "sigma2_mm": 4.128,
            "f_core": 0.5846
          },
          "y": {
            "sigma1_mm": 1.137,
            "sigma2_mm": 4.178,
            "f_core": 0.5909
          },
          "z": {
            "sigma1_mm": 1.2,
            "sigma2_mm": 4.371,
            "f_core": 0.6731
          }
        }
      },
      "80%": {
        "efficiency": 0.8,
        "coords": {
          "x": {
            "sigma1_mm": 1.119,
            "sigma2_mm": 4.128,
            "f_core": 0.7278
          },
          "y": {
            "sigma1_mm": 1.137,
            "sigma2_mm": 4.178,
            "f_core": 0.7398
          },
          "z": {
            "sigma1_mm": 1.2,
            "sigma2_mm": 4.371,
            "f_core": 0.8981
          }
        }
      },
      "60%": {
        "efficiency": 0.6,
        "coords": {
          "x": {
            "sigma1_mm": 1.119,
            "sigma2_mm": 4.128,
            "f_core": 0.8195
          },
          "y": {
            "sigma1_mm": 1.137,
            "sigma2_mm": 4.178,
            "f_core": 0.8258
          },
          "z": {
            "sigma1_mm": 1.2,
            "sigma2_mm": 4.371,
            "f_core": 0.951
          }
        }
      }
    },
    "BGO": {
      "none": {
        "efficiency": 1.0,
        "coords": {
          "x": {
            "sigma1_mm": 0.796,
            "sigma2_mm": 2.505,
            "f_core": 0.7159
          },
          "y": {
            "sigma1_mm": 0.816,
            "sigma2_mm": 2.586,
            "f_core": 0.7365
          },
          "z": {
            "sigma1_mm": 0.959,
            "sigma2_mm": 2.588,
            "f_core": 0.8208
          }
        }
      },
      "80%": {
        "efficiency": 0.8,
        "coords": {
          "x": {
            "sigma1_mm": 0.796,
            "sigma2_mm": 2.505,
            "f_core": 0.8053
          },
          "y": {
            "sigma1_mm": 0.816,
            "sigma2_mm": 2.586,
            "f_core": 0.8282
          },
          "z": {
            "sigma1_mm": 0.959,
            "sigma2_mm": 2.588,
            "f_core": 0.9587
          }
        }
      },
      "60%": {
        "efficiency": 0.6,
        "coords": {
          "x": {
            "sigma1_mm": 0.796,
            "sigma2_mm": 2.505,
            "f_core": 0.8456
          },
          "y": {
            "sigma1_mm": 0.816,
            "sigma2_mm": 2.586,
            "f_core": 0.8661
          },
          "z": {
            "sigma1_mm": 0.959,
            "sigma2_mm": 2.588,
            "f_core": 0.9626
          }
        }
      }
    }
  }
}